[{"testNumber": 0, "method": "getStopInfo", "result": 0, "message": "OK"}, {"testNumber": 1, "method": "getStopInfo", "result": 0, "message": "OK"}, {"testNumber": 2, "method": "getStopInfo", "result": 99, "message": "Test is a dummy"}, {"testNumber": 3, "method": "getStopInfo", "result": 99, "message": "Test is a dummy"}, {"testNumber": 4, "method": "getStopInfo", "result": 99, "message": "Test is a dummy"}, {"testNumber": 5, "method": "getStopInfo", "result": 99, "message": "Test is a dummy"}, {"testNumber": 10, "method": "getRouteInfo", "result": 0, "message": "OK"}, {"testNumber": 11, "method": "getRouteInfo", "result": 0, "message": "OK"}, {"testNumber": 12, "method": "getRouteInfo", "result": 0, "message": "OK"}, {"testNumber": 13, "method": "getRouteInfo", "result": 0, "message": "OK"}, {"testNumber": 14, "method": "getStopInfo", "result": 99, "message": "Test is a dummy"}, {"testNumber": 15, "method": "getStopInfo", "result": 99, "message": "Test is a dummy"}, {"testNumber": 20, "method": "getVehiclesInfo", "result": 0, "message": "OK"}, {"testNumber": 21, "method": "getVehiclesInfo", "result": 0, "message": "OK"}, {"testNumber": 22, "method": "getVehiclesInfo", "result": 0, "message": "OK"}, {"testNumber": 23, "method": "getVehiclesInfo", "result": 0, "message": "OK"}, {"testNumber": 24, "method": "getStopInfo", "result": 99, "message": "Test is a dummy"}, {"testNumber": 25, "method": "getStopInfo", "result": 99, "message": "Test is a dummy"}, {"testNumber": 30, "method": "getVehiclesInfoWithRegion", "result": 0, "message": "OK"}, {"testNumber": 31, "method": "getVehiclesInfoWithRegion", "result": 0, "message": "OK"}, {"testNumber": 32, "method": "getVehiclesInfoWithRegion", "result": 0, "message": "OK"}, {"testNumber": 33, "method": "getVehiclesInfoWithRegion", "result": 0, "message": "OK"}, {"testNumber": 34, "method": "getStopInfo", "result": 99, "message": "Test is a dummy"}, {"testNumber": 35, "method": "getStopInfo", "result": 99, "message": "Test is a dummy"}, {"testNumber": 40, "method": "getLayerRegions", "result": 1, "message": "Failed to get info"}, {"testNumber": 40, "method": "getLayerRegions", "result": 1, "message": "Failed to get info"}, {"testNumber": 40, "method": "getLayerRegions", "result": 1, "message": "Failed to get info"}, {"testNumber": 41, "method": "getLayerRegions", "result": 1, "message": "Failed to get info"}, {"testNumber": 41, "method": "getLayerRegions", "result": 1, "message": "Failed to get info"}, {"testNumber": 41, "method": "getLayerRegions", "result": 1, "message": "Failed to get info"}, {"testNumber": 42, "method": "getLayerRegions", "result": 0, "message": "OK"}, {"testNumber": 43, "method": "getLayerRegions", "result": 0, "message": "OK"}, {"testNumber": 44, "method": "getLayerRegions", "result": 0, "message": "OK"}, {"testNumber": 45, "method": "getLayerRegions", "result": 0, "message": "OK"}]